xetherscan/__init__.py
xetherscan/xetherscan.py
xetherscan-0.0.1.dist-info/LICENSE
xetherscan-0.0.1.dist-info/METADATA
xetherscan-0.0.1.dist-info/WHEEL
xetherscan-0.0.1.dist-info/top_level.txt
xetherscan-0.0.1.dist-info/RECORD
