Metadata-Version: 2.1
Name: xetherscan
Version: 0.0.1
Summary: Etherscan.io API wrapper
Home-page: https://github.com/neoctobers/xetherscan
Author: @neoctobers
Author-email: neoctobers@gmail.com
License: UNKNOWN
Platform: UNKNOWN
Classifier: Programming Language :: Python :: 3
Classifier: License :: OSI Approved :: MIT License
Classifier: Operating System :: OS Independent
